decbot/__init__.py
decbot/__main__.py
decbot/audio/__init__.py
decbot/audio/error.py
decbot/audio/mixer.py
decbot/audio/request.py
decbot/audio/tts.py
decbot/bot/__init__.py
decbot/bot/error.py
decbot/bot/text.py
decbot/bot/util.py
decbot/bot/voice.py
decbot/config/__init__.py
decbot/config/error.py
decbot/config/loader.py
decbot-1.0.0.dist-info/LICENSE
decbot-1.0.0.dist-info/METADATA
decbot-1.0.0.dist-info/WHEEL
decbot-1.0.0.dist-info/entry_points.txt
decbot-1.0.0.dist-info/top_level.txt
decbot-1.0.0.dist-info/RECORD
