Metadata-Version: 2.1
Name: decbot
Version: 1.0.0
Summary: a Discord bot that uses DECtalk text-to-speech
Home-page: https://github.com/wquist/DECbot
Author: Wyatt Lindquist
Author-email: git.wquist@gmail.com
License: MIT
Platform: UNKNOWN
Classifier: Programming Language :: Python :: 3.7
Classifier: License :: OSI Approved :: MIT License
Classifier: Operating System :: Unix
Requires-Dist: discord.py
Requires-Dist: pydub
Requires-Dist: pynacl
Requires-Dist: pyyaml
